micom/__init__.py
micom/algorithms.py
micom/annotation.py
micom/community.py
micom/db.py
micom/deps.py
micom/duality.py
micom/elasticity.py
micom/logger.py
micom/main.py
micom/measures.py
micom/media.py
micom/optcom.py
micom/problems.py
micom/qiime_formats.py
micom/solution.py
micom/stats.py
micom/taxonomy.py
micom/util.py
micom/data/__init__.py
micom/viz/__init__.py
micom/viz/core.py
micom/viz/exchanges.py
micom/viz/growth.py
micom/viz/prediction.py
micom/viz/tradeoff.py
micom/workflows/__init__.py
micom/workflows/build.py
micom/workflows/core.py
micom/workflows/db_media.py
micom/workflows/grow.py
micom/workflows/media.py
micom/workflows/tradeoff.py
PhyloMICOM-0.1.0.dist-info/METADATA
PhyloMICOM-0.1.0.dist-info/WHEEL
PhyloMICOM-0.1.0.dist-info/top_level.txt
PhyloMICOM-0.1.0.dist-info/RECORD
