Metadata-Version: 2.1
Name: PhyloMICOM
Version: 0.1.0
Summary: A package for microbial community analysis
Home-page: https://github.com/sepideh-mofidifar/PhyloMICOM
Author: Sepideh Mofidifar
Author-email: s.mofidifar@gmail.com
License: UNKNOWN
Platform: UNKNOWN
Classifier: Programming Language :: Python :: 3
Classifier: License :: OSI Approved :: MIT License
Classifier: Operating System :: OS Independent
Requires-Python: >=3.6
Requires-Dist: micom
Requires-Dist: cobra
